MANIFEST.in
requirements.txt
setup.cfg
setup.py
beltway/__init__.py
beltway/autolog.py
beltway/client.py
beltway/util.py
beltway.egg-info/PKG-INFO
beltway.egg-info/SOURCES.txt
beltway.egg-info/dependency_links.txt
beltway.egg-info/not-zip-safe
beltway.egg-info/requires.txt
beltway.egg-info/top_level.txt
beltway/wamp/__init__.py
beltway/wamp/auth.py
beltway/wamp/const.py
beltway/wamp/exception.py
beltway/wamp/message.py
beltway/wamp/request.py
beltway/wamp/role.py
beltway/wamp/serializer.py
beltway/wamp/types.py
beltway/wamp/uri.py