Metadata-Version: 1.0
Name: beltway
Version: 0.8.1
Summary: Threaded WAMP client
Home-page: https://github.com/matthewh/beltway
Author: Unspecified
Author-email: UNKNOWN
License: MIT
Platform: UNKNOWN
